conn_replitdb/__init__.py
conn_replitdb-0.0.post1.dist-info/METADATA
conn_replitdb-0.0.post1.dist-info/WHEEL
conn_replitdb-0.0.post1.dist-info/top_level.txt
conn_replitdb-0.0.post1.dist-info/RECORD
